distest/__init__.py
distest/bot.py
distest/collector.py
distest/exceptions.py
distest/patches.py
distest/validate_discord_token.py
distest/TestInterface/__init__.py
distest/TestInterface/_embeds.py
distest/TestInterface/_guild_channel.py
distest/TestInterface/_helpers.py
distest/TestInterface/_message.py
distest/TestInterface/_oddballs.py
distest/TestInterface/_reaction.py
distest/TestInterface/_reply.py
distest/TestInterface/_voice.py
distest/TestInterface/_wait_for.py
distest-0.6.2.dist-info/LICENSE
distest-0.6.2.dist-info/METADATA
distest-0.6.2.dist-info/WHEEL
distest-0.6.2.dist-info/top_level.txt
distest-0.6.2.dist-info/RECORD
