Metadata-Version: 2.1
Name: distest
Version: 0.6.2
Summary: Automate the testing of discord bots... With discord bots!
Home-page: http://github.com/JakeCover/distest
Author: Jake Cover
Author-email: python@jakecover.me
License: MIT
Keywords: Discord,Discord.py,Unit Test,Test,Distest,Discord Testing,Testing
Platform: UNKNOWN
Classifier: License :: OSI Approved :: MIT License
Classifier: Intended Audience :: Developers
Classifier: Natural Language :: English
Classifier: Operating System :: OS Independent
Classifier: Programming Language :: Python :: 3.6
Classifier: Programming Language :: Python :: 3.7
Classifier: Programming Language :: Python :: 3.8
Classifier: Programming Language :: Python :: 3.9
Classifier: Topic :: Internet
Classifier: Topic :: Software Development :: Testing :: Unit
Classifier: Topic :: Software Development :: Libraries
Classifier: Topic :: Software Development :: Libraries :: Python Modules
Classifier: Topic :: Utilities
Requires-Dist: discord.py (<1.7.0,>=1.5.0)
